pycoin/__init__.py
pycoin/market_data_gathering/__init__.py
pycoin/market_data_gathering/market_processing.py
pycoin/market_data_gathering/trend_filters.py
pycoin/market_data_kline_plots/__init__.py
pycoin/market_data_kline_plots/market_plotter.py
pythoncoin-1.0.3.dist-info/METADATA
pythoncoin-1.0.3.dist-info/WHEEL
pythoncoin-1.0.3.dist-info/top_level.txt
pythoncoin-1.0.3.dist-info/RECORD
