Metadata-Version: 2.1
Name: pythoncoin
Version: 1.0.3
Summary: a packege to make some algorithmic trading analyses easy.
Home-page: https://github.com/hadif1999/pycoin
Author: Hadi Fathipour
Author-email: hadi9628983@gmail.com
License: MIT
Classifier: Programming Language :: Python :: 3
Classifier: License :: OSI Approved :: MIT License
Classifier: Operating System :: OS Independent
Requires-Dist: plotly
Requires-Dist: pandas
Requires-Dist: numpy
Requires-Dist: kucoin-python
